AUTHORS
LICENSE
MANIFEST.in
README
setup.py
src/ovirt_engine_sdk.egg-info/PKG-INFO
src/ovirt_engine_sdk.egg-info/SOURCES.txt
src/ovirt_engine_sdk.egg-info/dependency_links.txt
src/ovirt_engine_sdk.egg-info/requires.txt
src/ovirt_engine_sdk.egg-info/top_level.txt
src/ovirtsdk/Example.py
src/ovirtsdk/__init__.py
src/ovirtsdk/api.py
src/ovirtsdk/test.py
src/ovirtsdk/infrastructure/__init__.py
src/ovirtsdk/infrastructure/brokers.py
src/ovirtsdk/infrastructure/cache.py
src/ovirtsdk/infrastructure/common.py
src/ovirtsdk/infrastructure/connectionspool.py
src/ovirtsdk/infrastructure/context.py
src/ovirtsdk/infrastructure/contextmanager.py
src/ovirtsdk/infrastructure/errors.py
src/ovirtsdk/infrastructure/proxy.py
src/ovirtsdk/utils/__init__.py
src/ovirtsdk/utils/comperator.py
src/ovirtsdk/utils/filterhelper.py
src/ovirtsdk/utils/ordereddict.py
src/ovirtsdk/utils/parsehelper.py
src/ovirtsdk/utils/reflectionhelper.py
src/ovirtsdk/utils/searchhelper.py
src/ovirtsdk/utils/synchronizationhelper.py
src/ovirtsdk/utils/urlhelper.py
src/ovirtsdk/web/__init__.py
src/ovirtsdk/web/connection.py
src/ovirtsdk/web/cookiejaradapter.py
src/ovirtsdk/web/httpsconnection.py
src/ovirtsdk/xml/__init__.py
src/ovirtsdk/xml/params.py