Metadata-Version: 1.1
Name: ovirt-engine-sdk
Version: 3.2.0.11-SNAPSHOT
Summary: A SDK interface to oVirt Virtualization
Home-page: http://www.ovirt.org/wiki/SDK
Author: Michael Pasternak
Author-email: mpastern@redhat.com
License: ASL2
Platform: UNKNOWN
Classifier: Development Status :: 4 - Beta
Classifier: Environment :: Console
Classifier: Intended Audience :: System Administrators
Classifier: License :: OSI Approved :: Apache Software License
Classifier: Operating System :: OS Independent
Classifier: Programming Language :: Python :: 2.6
